{"text": "          my burden. And she\u2019s absolutely right. The\n             Defendant has every right to remain silent,\n\n\n\n                                    13\n\f            and he exercised that right and that is\n            something that you cannot use against h", "meta": {"pile_set_name": "FreeLaw"}, "source_fname": "data/pile_100.jsonl", "hash": "txorv65KOXW2kVY_HkAd4A", "n_tokens": 45, "tokens": ["          ", "my", "\u0120burden", ".", "\u0120And", "\u0120she", "\u00e2\u0122\u013b", "s", "\u0120absolutely", "\u0120right", ".", "\u0120The", "\u010a", "             ", "Defendant", "\u0120has", "\u0120every", "\u0120right", "\u0120to", "\u0120remain", "\u0120silent", ",", "\u010a\u010a\u010a\u010a", "                        ", "            ", "13", "\u010a\u010c", "            ", "and", "\u0120he", "\u0120exercised", "\u0120that", "\u0120right", "\u0120and", "\u0120that", "\u0120is", "\u010a", "            ", "something", "\u0120that", "\u0120you", "\u0120cannot", "\u0120use", "\u0120against", "\u0120h"]}